LICENSE
MANIFEST.in
README.md
setup.cfg
setup.py
cmsplugin_survey/__init__.py
cmsplugin_survey/admin.py
cmsplugin_survey/apps.py
cmsplugin_survey/cms_plugins.py
cmsplugin_survey/fields.py
cmsplugin_survey/models.py
cmsplugin_survey/tests.py
cmsplugin_survey/urls.py
cmsplugin_survey/views.py
cmsplugin_survey.egg-info/PKG-INFO
cmsplugin_survey.egg-info/SOURCES.txt
cmsplugin_survey.egg-info/dependency_links.txt
cmsplugin_survey.egg-info/requires.txt
cmsplugin_survey.egg-info/top_level.txt
cmsplugin_survey/locale/cs/LC_MESSAGES/django.mo
cmsplugin_survey/locale/cs/LC_MESSAGES/django.po
cmsplugin_survey/migrations/0001_initial.py
cmsplugin_survey/migrations/__init__.py
cmsplugin_survey/static/cmsplugin_survey/style.css
cmsplugin_survey/templates/cmsplugin_survey/default.html
cmsplugin_survey/templatetags/__init__.py
cmsplugin_survey/templatetags/survey.py